README.md
setup.cfg
setup.py
pymacaron_core/__init__.py
pymacaron_core/exceptions.py
pymacaron_core/models.py
pymacaron_core/test.py
pymacaron_core/utils.py
pymacaron_core.egg-info/PKG-INFO
pymacaron_core.egg-info/SOURCES.txt
pymacaron_core.egg-info/dependency_links.txt
pymacaron_core.egg-info/not-zip-safe
pymacaron_core.egg-info/requires.txt
pymacaron_core.egg-info/top_level.txt
pymacaron_core/swagger/__init__.py
pymacaron_core/swagger/api.py
pymacaron_core/swagger/apipool.py
pymacaron_core/swagger/client.py
pymacaron_core/swagger/request.py
pymacaron_core/swagger/server.py
pymacaron_core/swagger/spec.py
test/test_custom_format.py
test/test_model.py
test/test_model_inheritance.py
test/test_model_persistence.py
test/test_pep8.py
test/test_swagger_api.py
test/test_swagger_apipool.py
test/test_swagger_client.py
test/test_swagger_server.py
test/test_swagger_spec.py