Metadata-Version: 2.1
Name: pymacaron-core
Version: 1.0.173
Summary: Swagger + Flask + Bravado-core = auto-spawning of API server, client and data objects for Pymacaron
Home-page: https://github.com/pymacaron/pymacaron-core
Author: Erwan Lemonnier
Author-email: erwan@lemonnier.se
License: BSD
Platform: any
Classifier: Environment :: Web Environment
Classifier: Intended Audience :: Developers
Classifier: License :: OSI Approved :: BSD License
Classifier: Operating System :: OS Independent
Classifier: Programming Language :: Python
Classifier: Topic :: Internet :: WWW/HTTP :: Dynamic Content
Classifier: Topic :: Software Development :: Libraries :: Python Modules
